django_admin_contexts/__about__.py
django_admin_contexts/__init__.py
django_admin_contexts/admin.py
django_admin_contexts/apps.py
django_admin_contexts/forms.py
django_admin_contexts/models.py
django_admin_contexts/urls.py
django_admin_contexts/views.py
django_admin_contexts/migrations/0001_initial.py
django_admin_contexts/migrations/__init__.py
django_admin_contexts/templates/admin/app_list.html
django_admin_contexts/templatetags/django_admin_contexts_tags.py
django_admin_contexts-0.4.0.dist-info/METADATA
django_admin_contexts-0.4.0.dist-info/WHEEL
django_admin_contexts-0.4.0.dist-info/licenses/AUTHORS.md
django_admin_contexts-0.4.0.dist-info/licenses/LICENSE
django_admin_contexts-0.4.0.dist-info/RECORD
