Metadata-Version: 2.4
Name: django-admin-contexts
Version: 0.4.0
Summary: Contexts for Django Admin homepage
Project-URL: Homepage, https://github.com/matagus/django-admin-contexts
Project-URL: Issues, https://.github.com/matagus/django-admin-contexts/issues
Project-URL: Repository, https://github.com/matagus/django-admin-contexts
Project-URL: Changelog, https://githib.com/matagus/django-admin-contexts/releases
Project-URL: Pypi, https://pypi.org/project/django-admin-contexts
Author-email: Matias Agustin Mendez <matagus@gmail.com>
License-Expression: BSD-3-Clause
License-File: AUTHORS.md
License-File: LICENSE
Classifier: Development Status :: 5 - Production/Stable
Classifier: Environment :: Console
Classifier: Environment :: Web Environment
Classifier: Framework :: Django
Classifier: Framework :: Django :: 4.2
Classifier: Framework :: Django :: 5.0
Classifier: Framework :: Django :: 5.1
Classifier: Framework :: Django :: 5.2
Classifier: Intended Audience :: Developers
Classifier: License :: OSI Approved :: BSD License
Classifier: Natural Language :: English
Classifier: Programming Language :: Python
Classifier: Programming Language :: Python :: 3.9
Classifier: Programming Language :: Python :: 3.10
Classifier: Programming Language :: Python :: 3.11
Classifier: Programming Language :: Python :: 3.12
Classifier: Programming Language :: Python :: 3.13
Classifier: Programming Language :: Python :: 3.14
Classifier: Programming Language :: Python :: Implementation :: CPython
Classifier: Programming Language :: Python :: Implementation :: PyPy
Classifier: Topic :: Software Development :: Libraries
Requires-Python: >=3.9
Requires-Dist: django>=4.2
Provides-Extra: dev
Requires-Dist: django-debug-toolbar; extra == 'dev'
Requires-Dist: django-extensions; extra == 'dev'
Requires-Dist: ipython; extra == 'dev'
Requires-Dist: werkzeug; extra == 'dev'
